setup.py
snapbuy/__init__.py
snapbuy/client.py
snapbuy.egg-info/PKG-INFO
snapbuy.egg-info/SOURCES.txt
snapbuy.egg-info/dependency_links.txt
snapbuy.egg-info/not-zip-safe
snapbuy.egg-info/requires.txt
snapbuy.egg-info/top_level.txt