Metadata-Version: 1.0
Name: snapbuy
Version: 1.0
Summary: Snapbuy Python SDK
Home-page: UNKNOWN
Author: Minh Hoang TO
Author-email: hoang281283@gmail.com
License: UNKNOWN
Platform: UNKNOWN
